{
  "system_overview": {
    "status": "HEALTHY",
    "uptime_check": "2025-06-19T21:27:52.930581",
    "configurations_loaded": 7,
    "api_success_rate": "3/4"
  },
  "ml_pipeline": {
    "pipeline_functional": true,
    "inference_time_ms": 25.5,
    "batch_size": 5,
    "burch_alignment_factor": 0.98
  },
  "portfolio_engine": {
    "integrated": true,
    "portfolio_metrics": {
      "expected_return": 0.1186734632758966,
      "volatility": 0.21547067826867763,
      "sharpe_ratio": 1.4597218699668426,
      "var_95": -0.053213227475435804,
      "max_drawdown": -0.18407652294383073
    },
    "total_opportunities": 2
  },
  "monitoring_system": {
    "integrated": true,
    "health_status": "healthy",
    "overall_score": 0.85,
    "monitoring_active": true
  },
  "integration_score": {
    "total_score": 93.75,
    "grade": "A",
    "components": {
      "ml_pipeline": true,
      "api_endpoints": true,
      "portfolio_engine": true,
      "monitoring_system": true
    }
  },
  "chris_burch_readiness": {
    "ready": true,
    "readiness_score": 1.0,
    "burch_alignment": 0.98,
    "capabilities": {
      "aesthetic_analysis": true,
      "portfolio_optimization": true,
      "trend_prediction": true,
      "full_integration": true
    },
    "recommendation": "DEPLOY"
  }
}